flask_guardian/__init__.py
flask_guardian/rules.py
flask_guardian/validator.py
flask_guardian/utils/conditions.py
flask_guardian/utils/errors.py
flask_guardian-0.1.1.dist-info/METADATA
flask_guardian-0.1.1.dist-info/WHEEL
flask_guardian-0.1.1.dist-info/licenses/LICENSE
flask_guardian-0.1.1.dist-info/RECORD
