Metadata-Version: 2.1
Name: flask_guardian
Version: 0.1.1
Summary: A small flask package
Project-URL: Homepage, https://github.com/antonin-alves/Flask-Guardian
Project-URL: Bug Tracker, https://github.com/antonin-alves/Flask-Guardian/issues
Author-email: Antonin Alves <antonin@alors-la.center>
License-File: LICENSE
Classifier: License :: OSI Approved :: MIT License
Classifier: Operating System :: OS Independent
Classifier: Programming Language :: Python :: 3
Requires-Python: >=3.7
